README.md
setup.cfg
setup.py
wfcli/__init__.py
wfcli/__main__.py
wfcli/tossl.py
wfcli/wfapi.py
wfcli.egg-info/PKG-INFO
wfcli.egg-info/SOURCES.txt
wfcli.egg-info/dependency_links.txt
wfcli.egg-info/entry_points.txt
wfcli.egg-info/requires.txt
wfcli.egg-info/top_level.txt