Metadata-Version: 1.1
Name: wfcli
Version: 0.4.5
Summary: WebFaction utilities
Home-page: https://github.com/dariosky/wfcli
Author: Dario Varotto
Author-email: dario.varotto@gmail.com
License: MIT
Keywords: deployment webfaction cli letsencrypt certificate
Platform: UNKNOWN
Classifier: Development Status :: 4 - Beta
Classifier: Intended Audience :: Developers
Classifier: Topic :: System :: Software Distribution
Classifier: License :: OSI Approved :: MIT License
Classifier: Programming Language :: Python :: 2
Classifier: Programming Language :: Python :: 2.6
Classifier: Programming Language :: Python :: 2.7
Classifier: Programming Language :: Python :: 3
Classifier: Programming Language :: Python :: 3.4
